.DS_Store
fusionlab/__init__.py
fusionlab/__version__.py
fusionlab/configs.py
fusionlab/classification/__init__.py
fusionlab/classification/base.py
fusionlab/classification/lstm.py
fusionlab/classification/vgg.py
fusionlab/datasets/__init__.py
fusionlab/datasets/a12lead.py
fusionlab/datasets/cinc2017.py
fusionlab/datasets/csvread.py
fusionlab/datasets/ludb.py
fusionlab/datasets/muse.py
fusionlab/datasets/utils.py
fusionlab/encoders/__init__.py
fusionlab/encoders/alexnet/__init__.py
fusionlab/encoders/alexnet/alexnet.py
fusionlab/encoders/alexnet/tfalexnet.py
fusionlab/encoders/convnext/__init__.py
fusionlab/encoders/convnext/convnext.py
fusionlab/encoders/efficientnet/__init__.py
fusionlab/encoders/efficientnet/efficientnet.py
fusionlab/encoders/inceptionv1/__init__.py
fusionlab/encoders/inceptionv1/inceptionv1.py
fusionlab/encoders/inceptionv1/tfinceptionv1.py
fusionlab/encoders/mit/__init__.py
fusionlab/encoders/mit/mit.py
fusionlab/encoders/resnetv1/__init__.py
fusionlab/encoders/resnetv1/resnetv1.py
fusionlab/encoders/resnetv1/tfresnetv1.py
fusionlab/encoders/vgg/__init__.py
fusionlab/encoders/vgg/tfvgg.py
fusionlab/encoders/vgg/vgg.py
fusionlab/encoders/vit/__init__.py
fusionlab/encoders/vit/vit.py
fusionlab/functional/__init__.py
fusionlab/functional/dice.py
fusionlab/functional/iou.py
fusionlab/functional/tfdice.py
fusionlab/functional/tfiou.py
fusionlab/layers/__init__.py
fusionlab/layers/base.py
fusionlab/layers/factories.py
fusionlab/layers/patch_embed/__init__.py
fusionlab/layers/patch_embed/patch_embedding.py
fusionlab/layers/selfattention/__init__.py
fusionlab/layers/selfattention/selfattention.py
fusionlab/layers/squeeze_excitation/__init__.py
fusionlab/layers/squeeze_excitation/se.py
fusionlab/layers/squeeze_excitation/tfse.py
fusionlab/losses/__init__.py
fusionlab/losses/dice/__init__.py
fusionlab/losses/dice/dice.py
fusionlab/losses/dice/tfdice.py
fusionlab/losses/diceloss/__init__.py
fusionlab/losses/diceloss/dice.py
fusionlab-0.1.13.dist-info/LICENSE
fusionlab-0.1.13.dist-info/METADATA
fusionlab-0.1.13.dist-info/WHEEL
fusionlab-0.1.13.dist-info/top_level.txt
fusionlab-0.1.13.dist-info/RECORD
