Metadata-Version: 2.1
Name: fusionlab
Version: 0.1.13
Summary: Useful packages for DL
Home-page: https://github.com/taipingeric/fusionlab
Author: Chih-Yang Li
Author-email: taipingeric@gmail.com
License: MIT
Classifier: License :: OSI Approved :: MIT License
Classifier: Programming Language :: Python :: 3
Classifier: Operating System :: OS Independent
Requires-Python: >=3.8.0
License-File: LICENSE
Requires-Dist: einops
Requires-Dist: tqdm
Requires-Dist: traceback2
Requires-Dist: pandas (>=1.5.3)
Requires-Dist: xmltodict
Requires-Dist: xlwt
Requires-Dist: scipy
Requires-Dist: wfdb
Provides-Extra: test
Requires-Dist: pytest ; extra == 'test'
Requires-Dist: mock ; extra == 'test'
Requires-Dist: pre-commit ; extra == 'test'
Requires-Dist: black (==22.3.0) ; extra == 'test'
Requires-Dist: flake8 (==4.0.1) ; extra == 'test'
Requires-Dist: flake8-docstrings (==1.6.0) ; extra == 'test'
Requires-Dist: torchvision ; extra == 'test'
Requires-Dist: tensorflow ; extra == 'test'
